<?xml version="1.0" encoding="UTF-8" ?>
<logfile manufacturer="Samsung" model="Nexus S" revision="4.4.4" swid="Radiobeacon" swver="0.7.9" exportver="0.7.9" >
<scan time="20140921133736" >
	<gps time="20140921133736" lng="8.772505345326342" lat="47.53008271530595" alt="519.0" hdg="66.13548278808594" spe="32.39082717895508" accuracy="15.0" />
		<gsmserving mcc="228" mnc="01" lac="3636" id="11808" act_id="11808" rnc="-1" psc="-1" ss="-79" act="EDGE" rxlev="17"/>
	<gps time="20140921133736" lng="8.772505345326342" lat="47.53008271530595" alt="519.0" hdg="66.13548278808594" spe="32.39082717895508" accuracy="15.0" />
</scan>
<scan time="20140921133739" >
	<gps time="20140921133739" lng="8.773770699026384" lat="47.53041092607687" alt="522.0" hdg="70.32427215576172" spe="32.702754974365234" accuracy="15.0" />
		<gsmserving mcc="228" mnc="01" lac="3636" id="11808" act_id="11808" rnc="-1" psc="-1" ss="-75" act="EDGE" rxlev="19"/>
	<gps time="20140921133739" lng="8.773770699026384" lat="47.53041092607687" alt="522.0" hdg="70.32427215576172" spe="32.702754974365234" accuracy="15.0" />
</scan>
<scan time="20140921133742" >
	<gps time="20140921133742" lng="8.77505751005152" lat="47.53070881921468" alt="523.0" hdg="70.82609558105469" spe="32.75665283203125" accuracy="15.0" />
		<gsmserving mcc="228" mnc="01" lac="3636" id="11808" act_id="11808" rnc="-1" psc="-1" ss="-69" act="EDGE" rxlev="22"/>
	<gps time="20140921133742" lng="8.77505751005152" lat="47.53070881921468" alt="523.0" hdg="70.82609558105469" spe="32.75665283203125" accuracy="15.0" />
</scan>
<scan time="20140921133745" >
	<gps time="20140921133745" lng="8.776323840921831" lat="47.53091836707712" alt="524.0" hdg="76.07197570800781" spe="32.97726058959961" accuracy="15.0" />
		<gsmserving mcc="228" mnc="01" lac="3636" id="11808" act_id="11808" rnc="-1" psc="-1" ss="-67" act="EDGE" rxlev="23"/>
	<gps time="20140921133745" lng="8.776323840921831" lat="47.53091836707712" alt="524.0" hdg="76.07197570800781" spe="32.97726058959961" accuracy="15.0" />
</scan>
<scan time="20140921133748" >
	<gps time="20140921133748" lng="8.777616850672064" lat="47.531088862722115" alt="526.0" hdg="77.91423797607422" spe="32.684326171875" accuracy="15.0" />
		<gsmserving mcc="228" mnc="01" lac="3636" id="11808" act_id="11808" rnc="-1" psc="-1" ss="-67" act="EDGE" rxlev="23"/>
	<gps time="20140921133748" lng="8.777616850672064" lat="47.531088862722115" alt="526.0" hdg="77.91423797607422" spe="32.684326171875" accuracy="15.0" />
</scan>
<scan time="20140921133751" >
	<gps time="20140921133751" lng="8.778937397344569" lat="47.531233626642134" alt="532.0" hdg="83.16328430175781" spe="32.692508697509766" accuracy="10.0" />
		<gsmserving mcc="228" mnc="01" lac="3636" id="11808" act_id="11808" rnc="-1" psc="-1" ss="-71" act="EDGE" rxlev="21"/>
	<gps time="20140921133751" lng="8.778937397344569" lat="47.531233626642134" alt="532.0" hdg="83.16328430175781" spe="32.692508697509766" accuracy="10.0" />
</scan>
<scan time="20140921133754" >
	<gps time="20140921133754" lng="8.780225188456887" lat="47.53130706343639" alt="534.0" hdg="83.07686614990234" spe="32.727447509765625" accuracy="10.0" />
		<gsmserving mcc="228" mnc="01" lac="3636" id="11808" act_id="11808" rnc="-1" psc="-1" ss="-73" act="EDGE" rxlev="20"/>
	<gps time="20140921133754" lng="8.780225188456887" lat="47.53130706343639" alt="534.0" hdg="83.07686614990234" spe="32.727447509765625" accuracy="10.0" />
</scan>
<scan time="20140921133757" >
	<gps time="20140921133757" lng="8.781515068449089" lat="47.53138617593686" alt="535.0" hdg="83.8774185180664" spe="32.76072311401367" accuracy="10.0" />
		<gsmserving mcc="228" mnc="01" lac="3636" id="11808" act_id="11808" rnc="-1" psc="-1" ss="-77" act="EDGE" rxlev="18"/>
	<gps time="20140921133757" lng="8.781515068449089" lat="47.53138617593686" alt="535.0" hdg="83.8774185180664" spe="32.76072311401367" accuracy="10.0" />
</scan>
<scan time="20140921133800" >
	<gps time="20140921133800" lng="8.782803733214562" lat="47.53146410439079" alt="535.0" hdg="84.5875244140625" spe="32.51427459716797" accuracy="10.0" />
		<gsmserving mcc="228" mnc="01" lac="3636" id="11808" act_id="11808" rnc="-1" psc="-1" ss="-81" act="EDGE" rxlev="16"/>
	<gps time="20140921133800" lng="8.782803733214562" lat="47.53146410439079" alt="535.0" hdg="84.5875244140625" spe="32.51427459716797" accuracy="10.0" />
</scan>
<scan time="20140921133803" >
	<gps time="20140921133803" lng="8.78410190375914" lat="47.531541972143096" alt="539.0" hdg="83.83251190185547" spe="32.79787063598633" accuracy="10.0" />
		<gsmserving mcc="228" mnc="01" lac="3636" id="11808" act_id="11808" rnc="-1" psc="-1" ss="-87" act="EDGE" rxlev="13"/>
	<gps time="20140921133803" lng="8.78410190375914" lat="47.531541972143096" alt="539.0" hdg="83.83251190185547" spe="32.79787063598633" accuracy="10.0" />
</scan>
<scan time="20140921133806" >
	<gps time="20140921133806" lng="8.785402512417411" lat="47.53162983280036" alt="538.0" hdg="84.39036560058594" spe="32.55385208129883" accuracy="10.0" />
		<gsmserving mcc="228" mnc="01" lac="3636" id="11808" act_id="11808" rnc="-1" psc="-1" ss="-91" act="EDGE" rxlev="11"/>
	<gps time="20140921133806" lng="8.785402512417411" lat="47.53162983280036" alt="538.0" hdg="84.39036560058594" spe="32.55385208129883" accuracy="10.0" />
</scan>
<scan time="20140921133809" >
	<gps time="20140921133809" lng="8.78671986675715" lat="47.53172036448001" alt="539.0" hdg="83.18611145019531" spe="33.04686737060547" accuracy="10.0" />
		<gsmserving mcc="228" mnc="01" lac="3636" id="11808" act_id="11808" rnc="-1" psc="-1" ss="-93" act="EDGE" rxlev="10"/>
	<gps time="20140921133809" lng="8.78671986675715" lat="47.53172036448001" alt="539.0" hdg="83.18611145019531" spe="33.04686737060547" accuracy="10.0" />
</scan>
<scan time="20140921133812" >
	<gps time="20140921133812" lng="8.78804282767844" lat="47.53180252264913" alt="535.0" hdg="84.73163604736328" spe="32.890079498291016" accuracy="10.0" />
		<gsmserving mcc="228" mnc="01" lac="3636" id="11808" act_id="11808" rnc="-1" psc="-1" ss="-97" act="EDGE" rxlev="8"/>
	<gps time="20140921133812" lng="8.78804282767844" lat="47.53180252264913" alt="535.0" hdg="84.73163604736328" spe="32.890079498291016" accuracy="10.0" />
</scan>
<scan time="20140921133815" >
	<gps time="20140921133815" lng="8.789351681752914" lat="47.53189841410412" alt="535.0" hdg="83.98160552978516" spe="32.997764587402344" accuracy="10.0" />
		<gsmserving mcc="228" mnc="01" lac="3636" id="11808" act_id="11808" rnc="-1" psc="-1" ss="-81" act="EDGE" rxlev="16"/>
	<gps time="20140921133815" lng="8.789351681752914" lat="47.53189841410412" alt="535.0" hdg="83.98160552978516" spe="32.997764587402344" accuracy="10.0" />
</scan>
<scan time="20140921133818" >
	<gps time="20140921133818" lng="8.790657574125113" lat="47.5319926303206" alt="532.0" hdg="84.10858917236328" spe="33.14448928833008" accuracy="10.0" />
		<gsmserving mcc="228" mnc="01" lac="1919" id="9942" act_id="9942" rnc="-1" psc="-1" ss="-73" act="EDGE" rxlev="20"/>
	<gps time="20140921133818" lng="8.790657574125113" lat="47.5319926303206" alt="532.0" hdg="84.10858917236328" spe="33.14448928833008" accuracy="10.0" />
</scan>
<scan time="20140921133821" >
	<gps time="20140921133821" lng="8.791959512279687" lat="47.53208552899114" alt="533.0" hdg="84.76716613769531" spe="33.28752899169922" accuracy="10.0" />
		<gsmserving mcc="228" mnc="01" lac="1919" id="9942" act_id="9942" rnc="-1" psc="-1" ss="-71" act="EDGE" rxlev="21"/>
	<gps time="20140921133821" lng="8.791959512279687" lat="47.53208552899114" alt="533.0" hdg="84.76716613769531" spe="33.28752899169922" accuracy="10.0" />
</scan>
<scan time="20140921133824" >
	<gps time="20140921133824" lng="8.79327740745463" lat="47.532163057161355" alt="534.0" hdg="85.04249572753906" spe="32.96992111206055" accuracy="10.0" />
		<gsmserving mcc="228" mnc="01" lac="1919" id="9942" act_id="9942" rnc="-1" psc="-1" ss="-69" act="EDGE" rxlev="22"/>
	<gps time="20140921133824" lng="8.79327740745463" lat="47.532163057161355" alt="534.0" hdg="85.04249572753906" spe="32.96992111206055" accuracy="10.0" />
</scan>
<scan time="20140921133827" >
	<gps time="20140921133827" lng="8.794584609386146" lat="47.53222734694989" alt="534.0" hdg="87.84235382080078" spe="32.903141021728516" accuracy="10.0" />
		<gsmserving mcc="228" mnc="01" lac="1919" id="9942" act_id="9942" rnc="-1" psc="-1" ss="-65" act="EDGE" rxlev="24"/>
	<gps time="20140921133827" lng="8.794584609386146" lat="47.53222734694989" alt="534.0" hdg="87.84235382080078" spe="32.903141021728516" accuracy="10.0" />
</scan>
<scan time="20140921133830" >
	<gps time="20140921133830" lng="8.79586095263731" lat="47.53225450529835" alt="530.0" hdg="89.18782806396484" spe="32.7630500793457" accuracy="10.0" />
		<gsmserving mcc="228" mnc="01" lac="1919" id="9942" act_id="9942" rnc="-1" psc="-1" ss="-61" act="EDGE" rxlev="26"/>
	<gps time="20140921133830" lng="8.79586095263731" lat="47.53225450529835" alt="530.0" hdg="89.18782806396484" spe="32.7630500793457" accuracy="10.0" />
</scan>
<scan time="20140921133833" >
	<gps time="20140921133833" lng="8.797156786441231" lat="47.53225947024521" alt="529.0" hdg="90.02928924560547" spe="32.7318229675293" accuracy="10.0" />
		<gsmserving mcc="228" mnc="01" lac="1919" id="9942" act_id="9942" rnc="-1" psc="-1" ss="-55" act="EDGE" rxlev="29"/>
	<gps time="20140921133833" lng="8.797156786441231" lat="47.53225947024521" alt="529.0" hdg="90.02928924560547" spe="32.7318229675293" accuracy="10.0" />
</scan>
<scan time="20140921133836" >
	<gps time="20140921133836" lng="8.798456692749236" lat="47.53225319915225" alt="528.0" hdg="91.59477996826172" spe="32.93501281738281" accuracy="5.0" />
		<gsmserving mcc="228" mnc="01" lac="1919" id="9942" act_id="9942" rnc="-1" psc="-1" ss="-53" act="EDGE" rxlev="30"/>
	<gps time="20140921133836" lng="8.798456692749236" lat="47.53225319915225" alt="528.0" hdg="91.59477996826172" spe="32.93501281738281" accuracy="5.0" />
</scan>
<scan time="20140921133839" >
	<gps time="20140921133839" lng="8.79975504394755" lat="47.532197762497084" alt="529.0" hdg="94.8463134765625" spe="32.60319900512695" accuracy="5.0" />
		<gsmserving mcc="228" mnc="01" lac="1919" id="9942" act_id="9942" rnc="-1" psc="-1" ss="-51" act="EDGE" rxlev="31"/>
	<gps time="20140921133839" lng="8.79975504394755" lat="47.532197762497084" alt="529.0" hdg="94.8463134765625" spe="32.60319900512695" accuracy="5.0" />
</scan>
<scan time="20140921133842" >
	<gps time="20140921133842" lng="8.801040201136413" lat="47.532109970796" alt="529.0" hdg="96.46389770507813" spe="32.67209243774414" accuracy="10.0" />
		<gsmserving mcc="228" mnc="01" lac="1919" id="9942" act_id="9942" rnc="-1" psc="-1" ss="-51" act="EDGE" rxlev="31"/>
	<gps time="20140921133842" lng="8.801040201136413" lat="47.532109970796" alt="529.0" hdg="96.46389770507813" spe="32.67209243774414" accuracy="10.0" />
</scan>
<scan time="20140921133845" >
	<gps time="20140921133845" lng="8.802327713754284" lat="47.531994963688405" alt="528.0" hdg="97.8281478881836" spe="32.500606536865234" accuracy="10.0" />
		<gsmserving mcc="228" mnc="01" lac="1919" id="9942" act_id="9942" rnc="-1" psc="-1" ss="-51" act="EDGE" rxlev="31"/>
	<gps time="20140921133845" lng="8.802327713754284" lat="47.531994963688405" alt="528.0" hdg="97.8281478881836" spe="32.500606536865234" accuracy="10.0" />
</scan>
<scan time="20140921133848" >
	<gps time="20140921133848" lng="8.80361215762453" lat="47.531868720452394" alt="525.0" hdg="98.98030090332031" spe="32.52988052368164" accuracy="10.0" />
		<gsmserving mcc="228" mnc="01" lac="1919" id="9942" act_id="9942" rnc="-1" psc="-1" ss="-59" act="EDGE" rxlev="27"/>
	<gps time="20140921133848" lng="8.80361215762453" lat="47.531868720452394" alt="525.0" hdg="98.98030090332031" spe="32.52988052368164" accuracy="10.0" />
</scan>
<scan time="20140921133851" >
	<gps time="20140921133851" lng="8.804892878050994" lat="47.531723144197215" alt="524.0" hdg="99.78426361083984" spe="32.54407501220703" accuracy="10.0" />
		<gsmserving mcc="228" mnc="01" lac="1919" id="9940" act_id="9940" rnc="-1" psc="-1" ss="-67" act="EDGE" rxlev="23"/>
	<gps time="20140921133851" lng="8.804892878050994" lat="47.531723144197215" alt="524.0" hdg="99.78426361083984" spe="32.54407501220703" accuracy="10.0" />
</scan>
<scan time="20140921133854" >
	<gps time="20140921133854" lng="8.8061708377882" lat="47.531569288387225" alt="529.0" hdg="100.612548828125" spe="32.078285217285156" accuracy="10.0" />
		<gsmserving mcc="228" mnc="01" lac="1919" id="9940" act_id="9940" rnc="-1" psc="-1" ss="-65" act="EDGE" rxlev="24"/>
	<gps time="20140921133854" lng="8.8061708377882" lat="47.531569288387225" alt="529.0" hdg="100.612548828125" spe="32.078285217285156" accuracy="10.0" />
</scan>
<scan time="20140921133857" >
	<gps time="20140921133857" lng="8.807474825973603" lat="47.53141605431825" alt="535.0" hdg="101.18384552001953" spe="32.505775451660156" accuracy="5.0" />
		<gsmserving mcc="228" mnc="01" lac="1919" id="9940" act_id="9940" rnc="-1" psc="-1" ss="-65" act="EDGE" rxlev="24"/>
	<gps time="20140921133857" lng="8.807474825973603" lat="47.53141605431825" alt="535.0" hdg="101.18384552001953" spe="32.505775451660156" accuracy="5.0" />
</scan>
<scan time="20140921133900" >
	<gps time="20140921133900" lng="8.808767065769102" lat="47.5312512939644" alt="538.0" hdg="100.9950180053711" spe="32.39800262451172" accuracy="5.0" />
		<gsmserving mcc="228" mnc="01" lac="1919" id="9940" act_id="9940" rnc="-1" psc="-1" ss="-67" act="EDGE" rxlev="23"/>
	<gps time="20140921133900" lng="8.808767065769102" lat="47.5312512939644" alt="538.0" hdg="100.9950180053711" spe="32.39800262451172" accuracy="5.0" />
</scan>
<scan time="20140921133903" >
	<gps time="20140921133903" lng="8.810037173434777" lat="47.531083691545845" alt="541.0" hdg="100.44062805175781" spe="32.31306076049805" accuracy="5.0" />
		<gsmserving mcc="228" mnc="01" lac="1919" id="9940" act_id="9940" rnc="-1" psc="-1" ss="-67" act="EDGE" rxlev="23"/>
	<gps time="20140921133903" lng="8.810037173434777" lat="47.531083691545845" alt="541.0" hdg="100.44062805175781" spe="32.31306076049805" accuracy="5.0" />
</scan>
<scan time="20140921133906" >
	<gps time="20140921133906" lng="8.811312204720476" lat="47.53091063201644" alt="545.0" hdg="101.27887725830078" spe="32.30052947998047" accuracy="5.0" />
		<gsmserving mcc="228" mnc="01" lac="1919" id="9940" act_id="9940" rnc="-1" psc="-1" ss="-69" act="EDGE" rxlev="22"/>
	<gps time="20140921133906" lng="8.811312204720476" lat="47.53091063201644" alt="545.0" hdg="101.27887725830078" spe="32.30052947998047" accuracy="5.0" />
</scan>
<scan time="20140921133909" >
	<gps time="20140921133909" lng="8.812588178643557" lat="47.530732991696574" alt="548.0" hdg="101.74534606933594" spe="32.22403335571289" accuracy="5.0" />
		<gsmserving mcc="228" mnc="01" lac="1919" id="9940" act_id="9940" rnc="-1" psc="-1" ss="-71" act="EDGE" rxlev="21"/>
	<gps time="20140921133909" lng="8.812588178643557" lat="47.530732991696574" alt="548.0" hdg="101.74534606933594" spe="32.22403335571289" accuracy="5.0" />
</scan>
<scan time="20140921133912" >
	<gps time="20140921133912" lng="8.813869010897829" lat="47.5305573050721" alt="550.0" hdg="101.28224182128906" spe="32.32902145385742" accuracy="5.0" />
		<gsmserving mcc="228" mnc="01" lac="1919" id="9940" act_id="9940" rnc="-1" psc="-1" ss="-73" act="EDGE" rxlev="20"/>
	<gps time="20140921133912" lng="8.813869010897829" lat="47.5305573050721" alt="550.0" hdg="101.28224182128906" spe="32.32902145385742" accuracy="5.0" />
</scan>
<scan time="20140921133915" >
	<gps time="20140921133915" lng="8.81513285577494" lat="47.530387875045925" alt="552.0" hdg="100.66685485839844" spe="32.12431335449219" accuracy="5.0" />
		<gsmserving mcc="228" mnc="01" lac="1919" id="9940" act_id="9940" rnc="-1" psc="-1" ss="-75" act="EDGE" rxlev="19"/>
	<gps time="20140921133915" lng="8.81513285577494" lat="47.530387875045925" alt="552.0" hdg="100.66685485839844" spe="32.12431335449219" accuracy="5.0" />
</scan>
<scan time="20140921133918" >
	<gps time="20140921133918" lng="8.816409142674203" lat="47.53021611730084" alt="556.0" hdg="100.2562255859375" spe="32.18720245361328" accuracy="5.0" />
		<gsmserving mcc="228" mnc="01" lac="1919" id="9940" act_id="9940" rnc="-1" psc="-1" ss="-77" act="EDGE" rxlev="18"/>
	<gps time="20140921133918" lng="8.816409142674203" lat="47.53021611730084" alt="556.0" hdg="100.2562255859375" spe="32.18720245361328" accuracy="5.0" />
</scan>
<scan time="20140921133921" >
	<gps time="20140921133921" lng="8.817687990284663" lat="47.5300483786992" alt="556.0" hdg="100.35881805419922" spe="32.43117904663086" accuracy="10.0" />
		<gsmserving mcc="228" mnc="01" lac="1919" id="9940" act_id="9940" rnc="-1" psc="-1" ss="-77" act="EDGE" rxlev="18"/>
	<gps time="20140921133921" lng="8.817687990284663" lat="47.5300483786992" alt="556.0" hdg="100.35881805419922" spe="32.43117904663086" accuracy="10.0" />
</scan>
<scan time="20140921133924" >
	<gps time="20140921133924" lng="8.81895420191884" lat="47.52988523053682" alt="557.0" hdg="101.0125961303711" spe="32.27863693237305" accuracy="10.0" />
		<gsmserving mcc="228" mnc="01" lac="1919" id="9940" act_id="9940" rnc="-1" psc="-1" ss="-79" act="EDGE" rxlev="17"/>
	<gps time="20140921133924" lng="8.81895420191884" lat="47.52988523053682" alt="557.0" hdg="101.0125961303711" spe="32.27863693237305" accuracy="10.0" />
</scan>
<scan time="20140921133927" >
	<gps time="20140921133927" lng="8.820227243318607" lat="47.529721123629116" alt="566.0" hdg="100.69926452636719" spe="32.28519058227539" accuracy="10.0" />
		<gsmserving mcc="228" mnc="01" lac="1919" id="9940" act_id="9940" rnc="-1" psc="-1" ss="-81" act="EDGE" rxlev="16"/>
	<gps time="20140921133927" lng="8.820227243318607" lat="47.529721123629116" alt="566.0" hdg="100.69926452636719" spe="32.28519058227539" accuracy="10.0" />
</scan>
<scan time="20140921133930" >
	<gps time="20140921133930" lng="8.821521123483704" lat="47.52956483948592" alt="568.0" hdg="100.42656707763672" spe="32.056556701660156" accuracy="10.0" />
		<gsmserving mcc="228" mnc="01" lac="1919" id="9940" act_id="9940" rnc="-1" psc="-1" ss="-83" act="EDGE" rxlev="15"/>
	<gps time="20140921133930" lng="8.821521123483704" lat="47.52956483948592" alt="568.0" hdg="100.42656707763672" spe="32.056556701660156" accuracy="10.0" />
</scan>
<scan time="20140921133933" >
	<gps time="20140921133933" lng="8.822800086756851" lat="47.52941001246873" alt="572.0" hdg="99.50526428222656" spe="32.273311614990234" accuracy="5.0" />
		<gsmserving mcc="228" mnc="01" lac="1919" id="9940" act_id="9940" rnc="-1" psc="-1" ss="-83" act="EDGE" rxlev="15"/>
	<gps time="20140921133933" lng="8.822800086756851" lat="47.52941001246873" alt="572.0" hdg="99.50526428222656" spe="32.273311614990234" accuracy="5.0" />
</scan>
<scan time="20140921133936" >
	<gps time="20140921133936" lng="8.82409099320048" lat="47.52926749612324" alt="577.0" hdg="97.87158203125" spe="32.52444076538086" accuracy="10.0" />
		<gsmserving mcc="228" mnc="01" lac="1919" id="9940" act_id="9940" rnc="-1" psc="-1" ss="-83" act="EDGE" rxlev="15"/>
	<gps time="20140921133936" lng="8.82409099320048" lat="47.52926749612324" alt="577.0" hdg="97.87158203125" spe="32.52444076538086" accuracy="10.0" />
</scan>
<scan time="20140921133939" >
	<gps time="20140921133939" lng="8.825385392629906" lat="47.529135407117934" alt="580.0" hdg="97.23379516601563" spe="32.30064392089844" accuracy="10.0" />
		<gsmserving mcc="228" mnc="01" lac="1919" id="9940" act_id="9940" rnc="-1" psc="-1" ss="-85" act="EDGE" rxlev="14"/>
	<gps time="20140921133939" lng="8.825385392629906" lat="47.529135407117934" alt="580.0" hdg="97.23379516601563" spe="32.30064392089844" accuracy="10.0" />
</scan>
<scan time="20140921133942" >
	<gps time="20140921133942" lng="8.826659895028193" lat="47.52902254963941" alt="579.0" hdg="97.63953399658203" spe="32.294681549072266" accuracy="10.0" />
		<gsmserving mcc="228" mnc="01" lac="1919" id="9940" act_id="9940" rnc="-1" psc="-1" ss="-87" act="EDGE" rxlev="13"/>
	<gps time="20140921133942" lng="8.826659895028193" lat="47.52902254963941" alt="579.0" hdg="97.63953399658203" spe="32.294681549072266" accuracy="10.0" />
</scan>
<scan time="20140921133945" >
	<gps time="20140921133945" lng="8.827939353304817" lat="47.52892926584864" alt="581.0" hdg="94.21086120605469" spe="32.410057067871094" accuracy="10.0" />
		<gsmserving mcc="228" mnc="01" lac="1919" id="9940" act_id="9940" rnc="-1" psc="-1" ss="-87" act="EDGE" rxlev="13"/>
	<gps time="20140921133945" lng="8.827939353304817" lat="47.52892926584864" alt="581.0" hdg="94.21086120605469" spe="32.410057067871094" accuracy="10.0" />
</scan>
<scan time="20140921133948" >
	<gps time="20140921133948" lng="8.829242705472552" lat="47.52888693917357" alt="583.0" hdg="92.87049102783203" spe="32.35090255737305" accuracy="10.0" />
		<gsmserving mcc="228" mnc="01" lac="1919" id="9940" act_id="9940" rnc="-1" psc="-1" ss="-87" act="EDGE" rxlev="13"/>
	<gps time="20140921133948" lng="8.829242705472552" lat="47.52888693917357" alt="583.0" hdg="92.87049102783203" spe="32.35090255737305" accuracy="10.0" />
</scan>
<scan time="20140921133951" >
	<gps time="20140921133951" lng="8.830547953975756" lat="47.52885274092162" alt="585.0" hdg="91.46551513671875" spe="32.34615707397461" accuracy="10.0" />
		<gsmserving mcc="228" mnc="01" lac="1919" id="9940" act_id="9940" rnc="-1" psc="-1" ss="-87" act="EDGE" rxlev="13"/>
	<gps time="20140921133951" lng="8.830547953975756" lat="47.52885274092162" alt="585.0" hdg="91.46551513671875" spe="32.34615707397461" accuracy="10.0" />
</scan>
<scan time="20140921133954" >
	<gps time="20140921133954" lng="8.831858039275096" lat="47.52885751389577" alt="588.0" hdg="89.06681060791016" spe="32.66031265258789" accuracy="10.0" />
		<gsmserving mcc="228" mnc="01" lac="1919" id="9940" act_id="9940" rnc="-1" psc="-1" ss="-89" act="EDGE" rxlev="12"/>
	<gps time="20140921133954" lng="8.831858039275096" lat="47.52885751389577" alt="588.0" hdg="89.06681060791016" spe="32.66031265258789" accuracy="10.0" />
</scan>
<scan time="20140921133957" >
	<gps time="20140921133957" lng="8.833167877696104" lat="47.52887815863871" alt="590.0" hdg="87.87403106689453" spe="32.690547943115234" accuracy="5.0" />
		<gsmserving mcc="228" mnc="01" lac="1919" id="9940" act_id="9940" rnc="-1" psc="-1" ss="-91" act="EDGE" rxlev="11"/>
	<gps time="20140921133957" lng="8.833167877696104" lat="47.52887815863871" alt="590.0" hdg="87.87403106689453" spe="32.690547943115234" accuracy="5.0" />
</scan>
<scan time="20140921134000" >
	<gps time="20140921134000" lng="8.83447308577629" lat="47.52893753787939" alt="591.0" hdg="85.342529296875" spe="32.72108840942383" accuracy="10.0" />
		<gsmserving mcc="228" mnc="01" lac="1919" id="16377" act_id="16377" rnc="-1" psc="-1" ss="-91" act="EDGE" rxlev="11"/>
	<gps time="20140921134000" lng="8.83447308577629" lat="47.52893753787939" alt="591.0" hdg="85.342529296875" spe="32.72108840942383" accuracy="10.0" />
</scan>
<scan time="20140921134003" >
	<gps time="20140921134003" lng="8.835779188590601" lat="47.52901928188663" alt="591.0" hdg="84.33527374267578" spe="32.83193588256836" accuracy="10.0" />
		<gsmserving mcc="228" mnc="01" lac="1919" id="16377" act_id="16377" rnc="-1" psc="-1" ss="-87" act="EDGE" rxlev="13"/>
	<gps time="20140921134003" lng="8.835779188590601" lat="47.52901928188663" alt="591.0" hdg="84.33527374267578" spe="32.83193588256836" accuracy="10.0" />
</scan>
<scan time="20140921134006" >
	<gps time="20140921134006" lng="8.837072964491652" lat="47.52911344183703" alt="591.0" hdg="83.28002166748047" spe="32.60425567626953" accuracy="10.0" />
		<gsmserving mcc="228" mnc="01" lac="1919" id="16377" act_id="16377" rnc="-1" psc="-1" ss="-79" act="EDGE" rxlev="17"/>
	<gps time="20140921134006" lng="8.837072964491652" lat="47.52911344183703" alt="591.0" hdg="83.28002166748047" spe="32.60425567626953" accuracy="10.0" />
</scan>
<scan time="20140921134009" >
	<gps time="20140921134009" lng="8.838368398555017" lat="47.52925493254665" alt="593.0" hdg="79.77437591552734" spe="32.86466598510742" accuracy="10.0" />
		<gsmserving mcc="228" mnc="01" lac="1919" id="16377" act_id="16377" rnc="-1" psc="-1" ss="-77" act="EDGE" rxlev="18"/>
	<gps time="20140921134009" lng="8.838368398555017" lat="47.52925493254665" alt="593.0" hdg="79.77437591552734" spe="32.86466598510742" accuracy="10.0" />
</scan>
<scan time="20140921134012" >
	<gps time="20140921134012" lng="8.83962428236677" lat="47.529414505717185" alt="590.0" hdg="78.91386413574219" spe="33.26161193847656" accuracy="15.0" />
		<gsmserving mcc="228" mnc="01" lac="1919" id="16377" act_id="16377" rnc="-1" psc="-1" ss="-75" act="EDGE" rxlev="19"/>
	<gps time="20140921134012" lng="8.83962428236677" lat="47.529414505717185" alt="590.0" hdg="78.91386413574219" spe="33.26161193847656" accuracy="15.0" />
</scan>
<scan time="20140921134015" >
	<gps time="20140921134015" lng="8.840904221570606" lat="47.5295991084907" alt="590.0" hdg="78.19232940673828" spe="33.27233123779297" accuracy="15.0" />
		<gsmserving mcc="228" mnc="01" lac="1919" id="16377" act_id="16377" rnc="-1" psc="-1" ss="-71" act="EDGE" rxlev="21"/>
	<gps time="20140921134015" lng="8.840904221570606" lat="47.5295991084907" alt="590.0" hdg="78.19232940673828" spe="33.27233123779297" accuracy="15.0" />
</scan>
<scan time="20140921134018" >
	<gps time="20140921134018" lng="8.842167725821565" lat="47.529749771432016" alt="587.0" hdg="79.45255279541016" spe="32.98167037963867" accuracy="15.0" />
		<gsmserving mcc="228" mnc="01" lac="1919" id="16377" act_id="16377" rnc="-1" psc="-1" ss="-67" act="EDGE" rxlev="23"/>
	<gps time="20140921134018" lng="8.842167725821565" lat="47.529749771432016" alt="587.0" hdg="79.45255279541016" spe="32.98167037963867" accuracy="15.0" />
</scan>
<scan time="20140921134021" >
	<gps time="20140921134021" lng="8.84345052546718" lat="47.52988924169598" alt="589.0" hdg="79.76424407958984" spe="33.06281280517578" accuracy="15.0" />
		<gsmserving mcc="228" mnc="01" lac="1919" id="16377" act_id="16377" rnc="-1" psc="-1" ss="-67" act="EDGE" rxlev="23"/>
	<gps time="20140921134021" lng="8.84345052546718" lat="47.52988924169598" alt="589.0" hdg="79.76424407958984" spe="33.06281280517578" accuracy="15.0" />
</scan>
<scan time="20140921134024" >
	<gps time="20140921134024" lng="8.84473649733849" lat="47.530004650223944" alt="589.0" hdg="82.07462310791016" spe="32.60453414916992" accuracy="15.0" />
		<gsmserving mcc="228" mnc="01" lac="1919" id="16377" act_id="16377" rnc="-1" psc="-1" ss="-65" act="EDGE" rxlev="24"/>
	<gps time="20140921134024" lng="8.84473649733849" lat="47.530004650223944" alt="589.0" hdg="82.07462310791016" spe="32.60453414916992" accuracy="15.0" />
</scan>
<scan time="20140921134027" >
	<gps time="20140921134027" lng="8.846040773804333" lat="47.53011650580212" alt="585.0" hdg="82.45794677734375" spe="33.13897705078125" accuracy="10.0" />
		<gsmserving mcc="228" mnc="01" lac="1919" id="16377" act_id="16377" rnc="-1" psc="-1" ss="-63" act="EDGE" rxlev="25"/>
	<gps time="20140921134027" lng="8.846040773804333" lat="47.53011650580212" alt="585.0" hdg="82.45794677734375" spe="33.13897705078125" accuracy="10.0" />
</scan>
<scan time="20140921134030" >
	<gps time="20140921134030" lng="8.847351879800536" lat="47.53020030682896" alt="583.0" hdg="84.3282470703125" spe="33.17557907104492" accuracy="10.0" />
		<gsmserving mcc="228" mnc="01" lac="1919" id="16377" act_id="16377" rnc="-1" psc="-1" ss="-61" act="EDGE" rxlev="26"/>
	<gps time="20140921134030" lng="8.847351879800536" lat="47.53020030682896" alt="583.0" hdg="84.3282470703125" spe="33.17557907104492" accuracy="10.0" />
</scan>
<scan time="20140921134033" >
	<gps time="20140921134033" lng="8.848658319186283" lat="47.5302554017943" alt="582.0" hdg="87.0018539428711" spe="32.857967376708984" accuracy="10.0" />
		<gsmserving mcc="228" mnc="01" lac="1919" id="16377" act_id="16377" rnc="-1" psc="-1" ss="-59" act="EDGE" rxlev="27"/>
	<gps time="20140921134033" lng="8.848658319186283" lat="47.5302554017943" alt="582.0" hdg="87.0018539428711" spe="32.857967376708984" accuracy="10.0" />
</scan>
<scan time="20140921134036" >
	<gps time="20140921134036" lng="8.849981480258013" lat="47.530306971801984" alt="582.0" hdg="89.35775756835938" spe="32.8316535949707" accuracy="5.0" />
		<gsmserving mcc="228" mnc="01" lac="1919" id="16377" act_id="16377" rnc="-1" psc="-1" ss="-55" act="EDGE" rxlev="29"/>
	<gps time="20140921134036" lng="8.849981480258013" lat="47.530306971801984" alt="582.0" hdg="89.35775756835938" spe="32.8316535949707" accuracy="5.0" />
</scan>
<scan time="20140921134039" >
	<gps time="20140921134039" lng="8.85129646142271" lat="47.53032630893932" alt="582.0" hdg="90.47821807861328" spe="32.95286560058594" accuracy="10.0" />
		<gsmserving mcc="228" mnc="01" lac="1919" id="16377" act_id="16377" rnc="-1" psc="-1" ss="-53" act="EDGE" rxlev="30"/>
	<gps time="20140921134039" lng="8.85129646142271" lat="47.53032630893932" alt="582.0" hdg="90.47821807861328" spe="32.95286560058594" accuracy="10.0" />
</scan>
<scan time="20140921134042" >
	<gps time="20140921134042" lng="8.852607476184977" lat="47.530310445403096" alt="580.0" hdg="92.24857330322266" spe="32.917823791503906" accuracy="10.0" />
		<gsmserving mcc="228" mnc="01" lac="1919" id="16377" act_id="16377" rnc="-1" psc="-1" ss="-51" act="EDGE" rxlev="31"/>
	<gps time="20140921134042" lng="8.852607476184977" lat="47.530310445403096" alt="580.0" hdg="92.24857330322266" spe="32.917823791503906" accuracy="10.0" />
</scan>
<scan time="20140921134045" >
	<gps time="20140921134045" lng="8.853897835901005" lat="47.530252983942155" alt="577.0" hdg="92.7637710571289" spe="32.91130065917969" accuracy="10.0" />
		<gsmserving mcc="228" mnc="01" lac="1919" id="16377" act_id="16377" rnc="-1" psc="-1" ss="-53" act="EDGE" rxlev="30"/>
	<gps time="20140921134045" lng="8.853897835901005" lat="47.530252983942155" alt="577.0" hdg="92.7637710571289" spe="32.91130065917969" accuracy="10.0" />
</scan>
<scan time="20140921134048" >
	<gps time="20140921134048" lng="8.85522035256013" lat="47.53020201668681" alt="578.0" hdg="93.42879486083984" spe="32.947784423828125" accuracy="10.0" />
		<gsmserving mcc="228" mnc="01" lac="1919" id="16377" act_id="16377" rnc="-1" psc="-1" ss="-55" act="EDGE" rxlev="29"/>
	<gps time="20140921134048" lng="8.85522035256013" lat="47.53020201668681" alt="578.0" hdg="93.42879486083984" spe="32.947784423828125" accuracy="10.0" />
</scan>
<scan time="20140921134051" >
	<gps time="20140921134051" lng="8.856523521904432" lat="47.5301612086557" alt="576.0" hdg="93.4595947265625" spe="32.75845718383789" accuracy="10.0" />
		<gsmserving mcc="228" mnc="01" lac="1919" id="16377" act_id="16377" rnc="-1" psc="-1" ss="-67" act="EDGE" rxlev="23"/>
	<gps time="20140921134051" lng="8.856523521904432" lat="47.5301612086557" alt="576.0" hdg="93.4595947265625" spe="32.75845718383789" accuracy="10.0" />
</scan>
<scan time="20140921134054" >
	<gps time="20140921134054" lng="8.857849264585942" lat="47.530115397928995" alt="578.0" hdg="92.53534698486328" spe="32.84953308105469" accuracy="5.0" />
		<gsmserving mcc="228" mnc="01" lac="1919" id="16377" act_id="16377" rnc="-1" psc="-1" ss="-71" act="EDGE" rxlev="21"/>
	<gps time="20140921134054" lng="8.857849264585942" lat="47.530115397928995" alt="578.0" hdg="92.53534698486328" spe="32.84953308105469" accuracy="5.0" />
</scan>
<scan time="20140921134057" >
	<gps time="20140921134057" lng="8.85915279866185" lat="47.53010629305069" alt="577.0" hdg="89.95930480957031" spe="32.86381530761719" accuracy="5.0" />
		<gsmserving mcc="228" mnc="01" lac="1919" id="16019" act_id="16019" rnc="-1" psc="-1" ss="-81" act="EDGE" rxlev="16"/>
	<gps time="20140921134057" lng="8.85915279866185" lat="47.53010629305069" alt="577.0" hdg="89.95930480957031" spe="32.86381530761719" accuracy="5.0" />
</scan>
<scan time="20140921134100" >
	<gps time="20140921134100" lng="8.86045635305332" lat="47.530119574183765" alt="578.0" hdg="88.77599334716797" spe="32.51837158203125" accuracy="5.0" />
		<gsmserving mcc="228" mnc="01" lac="1919" id="16019" act_id="16019" rnc="-1" psc="-1" ss="-83" act="EDGE" rxlev="15"/>
	<gps time="20140921134100" lng="8.86045635305332" lat="47.530119574183765" alt="578.0" hdg="88.77599334716797" spe="32.51837158203125" accuracy="5.0" />
</scan>
<scan time="20140921134103" >
	<gps time="20140921134103" lng="8.861760928796429" lat="47.530161660463214" alt="580.0" hdg="87.62317657470703" spe="32.58344268798828" accuracy="5.0" />
		<gsmserving mcc="228" mnc="01" lac="1919" id="16376" act_id="16376" rnc="-1" psc="-1" ss="-75" act="EDGE" rxlev="19"/>
	<gps time="20140921134103" lng="8.861760928796429" lat="47.530161660463214" alt="580.0" hdg="87.62317657470703" spe="32.58344268798828" accuracy="5.0" />
</scan>
<scan time="20140921134106" >
	<gps time="20140921134106" lng="8.863062643208705" lat="47.53020779941968" alt="583.0" hdg="87.5042953491211" spe="32.63766860961914" accuracy="5.0" />
		<gsmserving mcc="228" mnc="01" lac="1919" id="16376" act_id="16376" rnc="-1" psc="-1" ss="-73" act="EDGE" rxlev="20"/>
	<gps time="20140921134106" lng="8.863062643208705" lat="47.53020779941968" alt="583.0" hdg="87.5042953491211" spe="32.63766860961914" accuracy="5.0" />
</scan>
<scan time="20140921134109" >
	<gps time="20140921134109" lng="8.864361515415503" lat="47.53023965492073" alt="585.0" hdg="89.00304412841797" spe="32.395172119140625" accuracy="5.0" />
		<gsmserving mcc="228" mnc="01" lac="1919" id="16376" act_id="16376" rnc="-1" psc="-1" ss="-79" act="EDGE" rxlev="17"/>
	<gps time="20140921134109" lng="8.864361515415503" lat="47.53023965492073" alt="585.0" hdg="89.00304412841797" spe="32.395172119140625" accuracy="5.0" />
</scan>
<scan time="20140921134112" >
	<gps time="20140921134112" lng="8.8656676013772" lat="47.53027192628821" alt="583.0" hdg="88.9759521484375" spe="32.485286712646484" accuracy="5.0" />
		<gsmserving mcc="228" mnc="01" lac="1919" id="16376" act_id="16376" rnc="-1" psc="-1" ss="-83" act="EDGE" rxlev="15"/>
	<gps time="20140921134112" lng="8.8656676013772" lat="47.53027192628821" alt="583.0" hdg="88.9759521484375" spe="32.485286712646484" accuracy="5.0" />
</scan>
<scan time="20140921134115" >
	<gps time="20140921134115" lng="8.866971320086146" lat="47.53026167092851" alt="584.0" hdg="92.3091049194336" spe="32.67700958251953" accuracy="5.0" />
		<gsmserving mcc="228" mnc="01" lac="1919" id="16376" act_id="16376" rnc="-1" psc="-1" ss="-85" act="EDGE" rxlev="14"/>
	<gps time="20140921134115" lng="8.866971320086146" lat="47.53026167092851" alt="584.0" hdg="92.3091049194336" spe="32.67700958251953" accuracy="5.0" />
</scan>
<scan time="20140921134118" >
	<gps time="20140921134118" lng="8.868277246761691" lat="47.53019739994094" alt="584.0" hdg="95.35690307617188" spe="32.488197326660156" accuracy="5.0" />
		<gsmserving mcc="228" mnc="01" lac="1919" id="16376" act_id="16376" rnc="-1" psc="-1" ss="-87" act="EDGE" rxlev="13"/>
	<gps time="20140921134118" lng="8.868277246761691" lat="47.53019739994094" alt="584.0" hdg="95.35690307617188" spe="32.488197326660156" accuracy="5.0" />
</scan>
<scan time="20140921134121" >
	<gps time="20140921134121" lng="8.869561853198409" lat="47.53007475789626" alt="585.0" hdg="99.4813003540039" spe="32.67182159423828" accuracy="10.0" />
		<gsmserving mcc="228" mnc="01" lac="1919" id="16376" act_id="16376" rnc="-1" psc="-1" ss="-89" act="EDGE" rxlev="12"/>
	<gps time="20140921134121" lng="8.869561853198409" lat="47.53007475789626" alt="585.0" hdg="99.4813003540039" spe="32.67182159423828" accuracy="10.0" />
</scan>
<scan time="20140921134124" >
	<gps time="20140921134124" lng="8.870841211221512" lat="47.5298906521667" alt="581.0" hdg="103.35140228271484" spe="32.958614349365234" accuracy="10.0" />
		<gsmserving mcc="228" mnc="01" lac="1919" id="16376" act_id="16376" rnc="-1" psc="-1" ss="-89" act="EDGE" rxlev="12"/>
	<gps time="20140921134124" lng="8.870841211221512" lat="47.5298906521667" alt="581.0" hdg="103.35140228271484" spe="32.958614349365234" accuracy="10.0" />
</scan>
<scan time="20140921134127" >
	<gps time="20140921134127" lng="8.872101170457274" lat="47.529647145334444" alt="579.0" hdg="106.9321060180664" spe="33.0057487487793" accuracy="5.0" />
		<gsmserving mcc="228" mnc="01" lac="1919" id="16376" act_id="16376" rnc="-1" psc="-1" ss="-89" act="EDGE" rxlev="12"/>
	<gps time="20140921134127" lng="8.872101170457274" lat="47.529647145334444" alt="579.0" hdg="106.9321060180664" spe="33.0057487487793" accuracy="5.0" />
</scan>
<scan time="20140921134130" >
	<gps time="20140921134130" lng="8.873329071612478" lat="47.52935469313683" alt="577.0" hdg="111.1428451538086" spe="32.937686920166016" accuracy="5.0" />
		<gsmserving mcc="228" mnc="01" lac="1919" id="16376" act_id="16376" rnc="-1" psc="-1" ss="-93" act="EDGE" rxlev="10"/>
	<gps time="20140921134130" lng="8.873329071612478" lat="47.52935469313683" alt="577.0" hdg="111.1428451538086" spe="32.937686920166016" accuracy="5.0" />
</scan>
<scan time="20140921134133" >
	<gps time="20140921134133" lng="8.874536879055627" lat="47.52900447355488" alt="578.0" hdg="114.17074584960938" spe="32.964439392089844" accuracy="5.0" />
		<gsmserving mcc="228" mnc="01" lac="1919" id="30655" act_id="30655" rnc="-1" psc="-1" ss="-91" act="EDGE" rxlev="11"/>
	<gps time="20140921134133" lng="8.874536879055627" lat="47.52900447355488" alt="578.0" hdg="114.17074584960938" spe="32.964439392089844" accuracy="5.0" />
</scan>
<scan time="20140921134136" >
	<gps time="20140921134136" lng="8.875700179618384" lat="47.52861447707106" alt="578.0" hdg="117.08531951904297" spe="32.7618522644043" accuracy="5.0" />
		<gsmserving mcc="228" mnc="01" lac="1919" id="30655" act_id="30655" rnc="-1" psc="-1" ss="-87" act="EDGE" rxlev="13"/>
	<gps time="20140921134136" lng="8.875700179618384" lat="47.52861447707106" alt="578.0" hdg="117.08531951904297" spe="32.7618522644043" accuracy="5.0" />
</scan>
<scan time="20140921134139" >
	<gps time="20140921134139" lng="8.87686211185962" lat="47.52818698116126" alt="578.0" hdg="119.26538848876953" spe="32.71011734008789" accuracy="5.0" />
		<gsmserving mcc="228" mnc="01" lac="1919" id="30655" act_id="30655" rnc="-1" psc="-1" ss="-87" act="EDGE" rxlev="13"/>
	<gps time="20140921134139" lng="8.87686211185962" lat="47.52818698116126" alt="578.0" hdg="119.26538848876953" spe="32.71011734008789" accuracy="5.0" />
</scan>
<scan time="20140921134142" >
	<gps time="20140921134142" lng="8.878002620575643" lat="47.52773875481216" alt="581.0" hdg="119.83387756347656" spe="32.730628967285156" accuracy="5.0" />
		<gsmserving mcc="228" mnc="01" lac="1919" id="30655" act_id="30655" rnc="-1" psc="-1" ss="-87" act="EDGE" rxlev="13"/>
	<gps time="20140921134142" lng="8.878002620575643" lat="47.52773875481216" alt="581.0" hdg="119.83387756347656" spe="32.730628967285156" accuracy="5.0" />
</scan>
<scan time="20140921134145" >
	<gps time="20140921134145" lng="8.879137276085197" lat="47.52728852847369" alt="586.0" hdg="120.03022003173828" spe="32.669254302978516" accuracy="5.0" />
		<gsmserving mcc="228" mnc="01" lac="1919" id="30655" act_id="30655" rnc="-1" psc="-1" ss="-85" act="EDGE" rxlev="14"/>
	<gps time="20140921134145" lng="8.879137276085197" lat="47.52728852847369" alt="586.0" hdg="120.03022003173828" spe="32.669254302978516" accuracy="5.0" />
</scan>
<scan time="20140921134148" >
	<gps time="20140921134148" lng="8.880257573204913" lat="47.52684975459626" alt="587.0" hdg="119.39733123779297" spe="32.45497131347656" accuracy="5.0" />
		<gsmserving mcc="228" mnc="01" lac="1919" id="30655" act_id="30655" rnc="-1" psc="-1" ss="-83" act="EDGE" rxlev="15"/>
	<gps time="20140921134148" lng="8.880257573204913" lat="47.52684975459626" alt="587.0" hdg="119.39733123779297" spe="32.45497131347656" accuracy="5.0" />
</scan>
<scan time="20140921134151" >
	<gps time="20140921134151" lng="8.881399312899894" lat="47.52642554296602" alt="588.0" hdg="117.89874267578125" spe="32.635135650634766" accuracy="5.0" />
		<gsmserving mcc="228" mnc="01" lac="1919" id="30655" act_id="30655" rnc="-1" psc="-1" ss="-79" act="EDGE" rxlev="17"/>
	<gps time="20140921134151" lng="8.881399312899894" lat="47.52642554296602" alt="588.0" hdg="117.89874267578125" spe="32.635135650634766" accuracy="5.0" />
</scan>
<scan time="20140921134154" >
	<gps time="20140921134154" lng="8.88256831873211" lat="47.52603210900682" alt="590.0" hdg="115.52692413330078" spe="32.608551025390625" accuracy="5.0" />
		<gsmserving mcc="228" mnc="01" lac="1919" id="30655" act_id="30655" rnc="-1" psc="-1" ss="-77" act="EDGE" rxlev="18"/>
	<gps time="20140921134154" lng="8.88256831873211" lat="47.52603210900682" alt="590.0" hdg="115.52692413330078" spe="32.608551025390625" accuracy="5.0" />
</scan>
<scan time="20140921134157" >
	<gps time="20140921134157" lng="8.883752854844754" lat="47.52568319824243" alt="589.0" hdg="113.45448303222656" spe="32.31916427612305" accuracy="5.0" />
		<gsmserving mcc="228" mnc="01" lac="1919" id="30655" act_id="30655" rnc="-1" psc="-1" ss="-71" act="EDGE" rxlev="21"/>
	<gps time="20140921134157" lng="8.883752854844754" lat="47.52568319824243" alt="589.0" hdg="113.45448303222656" spe="32.31916427612305" accuracy="5.0" />
</scan>
<scan time="20140921134200" >
	<gps time="20140921134200" lng="8.884949948088584" lat="47.52536330240853" alt="589.0" hdg="111.15128326416016" spe="32.75395202636719" accuracy="5.0" />
		<gsmserving mcc="228" mnc="01" lac="1919" id="30655" act_id="30655" rnc="-1" psc="-1" ss="-67" act="EDGE" rxlev="23"/>
	<gps time="20140921134200" lng="8.884949948088584" lat="47.52536330240853" alt="589.0" hdg="111.15128326416016" spe="32.75395202636719" accuracy="5.0" />
</scan>
<scan time="20140921134203" >
	<gps time="20140921134203" lng="8.886172616579627" lat="47.52507438047506" alt="587.0" hdg="110.27349853515625" spe="32.39894485473633" accuracy="5.0" />
		<gsmserving mcc="228" mnc="01" lac="1919" id="30655" act_id="30655" rnc="-1" psc="-1" ss="-65" act="EDGE" rxlev="24"/>
	<gps time="20140921134203" lng="8.886172616579627" lat="47.52507438047506" alt="587.0" hdg="110.27349853515625" spe="32.39894485473633" accuracy="5.0" />
</scan>
<scan time="20140921134206" >
	<gps time="20140921134206" lng="8.887406228548423" lat="47.52475798060731" alt="588.0" hdg="109.93970489501953" spe="32.35502243041992" accuracy="10.0" />
		<gsmserving mcc="228" mnc="01" lac="1919" id="30655" act_id="30655" rnc="-1" psc="-1" ss="-61" act="EDGE" rxlev="26"/>
	<gps time="20140921134206" lng="8.887406228548423" lat="47.52475798060731" alt="588.0" hdg="109.93970489501953" spe="32.35502243041992" accuracy="10.0" />
</scan>
<scan time="20140921134209" >
	<gps time="20140921134209" lng="8.888623762932509" lat="47.52444590734422" alt="587.0" hdg="111.9913558959961" spe="32.60869598388672" accuracy="10.0" />
		<gsmserving mcc="228" mnc="01" lac="1919" id="30655" act_id="30655" rnc="-1" psc="-1" ss="-61" act="EDGE" rxlev="26"/>
	<gps time="20140921134209" lng="8.888623762932509" lat="47.52444590734422" alt="587.0" hdg="111.9913558959961" spe="32.60869598388672" accuracy="10.0" />
</scan>
<scan time="20140921134212" >
	<gps time="20140921134212" lng="8.889848444367269" lat="47.524098044941695" alt="590.0" hdg="112.7162094116211" spe="32.83149337768555" accuracy="10.0" />
		<gsmserving mcc="228" mnc="01" lac="1919" id="30655" act_id="30655" rnc="-1" psc="-1" ss="-55" act="EDGE" rxlev="29"/>
	<gps time="20140921134212" lng="8.889848444367269" lat="47.524098044941695" alt="590.0" hdg="112.7162094116211" spe="32.83149337768555" accuracy="10.0" />
</scan>
<scan time="20140921134215" >
	<gps time="20140921134215" lng="8.891002478007277" lat="47.52370073617505" alt="589.0" hdg="119.42350769042969" spe="32.91027069091797" accuracy="10.0" />
		<gsmserving mcc="228" mnc="01" lac="1919" id="30655" act_id="30655" rnc="-1" psc="-1" ss="-51" act="EDGE" rxlev="31"/>
	<gps time="20140921134215" lng="8.891002478007277" lat="47.52370073617505" alt="589.0" hdg="119.42350769042969" spe="32.91027069091797" accuracy="10.0" />
</scan>
<scan time="20140921134218" >
	<gps time="20140921134218" lng="8.892126361152522" lat="47.523238221139835" alt="590.0" hdg="123.83560943603516" spe="32.806068420410156" accuracy="10.0" />
		<gsmserving mcc="228" mnc="01" lac="1919" id="30655" act_id="30655" rnc="-1" psc="-1" ss="-51" act="EDGE" rxlev="31"/>
	<gps time="20140921134218" lng="8.892126361152522" lat="47.523238221139835" alt="590.0" hdg="123.83560943603516" spe="32.806068420410156" accuracy="10.0" />
</scan>
<scan time="20140921134221" >
	<gps time="20140921134221" lng="8.893193995256917" lat="47.52270307741063" alt="585.0" hdg="129.2688751220703" spe="33.3392448425293" accuracy="10.0" />
		<gsmserving mcc="228" mnc="01" lac="1919" id="30655" act_id="30655" rnc="-1" psc="-1" ss="-51" act="EDGE" rxlev="31"/>
	<gps time="20140921134221" lng="8.893193995256917" lat="47.52270307741063" alt="585.0" hdg="129.2688751220703" spe="33.3392448425293" accuracy="10.0" />
</scan>
<scan time="20140921134224" >
	<gps time="20140921134224" lng="8.894132981946253" lat="47.52208432117894" alt="578.0" hdg="135.4027099609375" spe="32.993343353271484" accuracy="10.0" />
		<gsmserving mcc="228" mnc="01" lac="1919" id="30655" act_id="30655" rnc="-1" psc="-1" ss="-55" act="EDGE" rxlev="29"/>
	<gps time="20140921134224" lng="8.894132981946253" lat="47.52208432117894" alt="578.0" hdg="135.4027099609375" spe="32.993343353271484" accuracy="10.0" />
</scan>
<scan time="20140921134227" >
	<gps time="20140921134227" lng="8.894990593554672" lat="47.5214240273914" alt="573.0" hdg="139.69163513183594" spe="33.162479400634766" accuracy="10.0" />
		<gsmserving mcc="228" mnc="01" lac="1919" id="16073" act_id="16073" rnc="-1" psc="-1" ss="-63" act="EDGE" rxlev="25"/>
	<gps time="20140921134227" lng="8.894990593554672" lat="47.5214240273914" alt="573.0" hdg="139.69163513183594" spe="33.162479400634766" accuracy="10.0" />
</scan>
<scan time="20140921134230" >
	<gps time="20140921134230" lng="8.895790008608145" lat="47.52073482180787" alt="572.0" hdg="143.3878936767578" spe="33.006263732910156" accuracy="10.0" />
		<gsmserving mcc="228" mnc="01" lac="1919" id="16073" act_id="16073" rnc="-1" psc="-1" ss="-61" act="EDGE" rxlev="26"/>
	<gps time="20140921134230" lng="8.895790008608145" lat="47.52073482180787" alt="572.0" hdg="143.3878936767578" spe="33.006263732910156" accuracy="10.0" />
</scan>
<scan time="20140921134233" >
	<gps time="20140921134233" lng="8.896585302465054" lat="47.520023020565546" alt="569.0" hdg="143.3878936767578" spe="32.42000198364258" accuracy="15.0" />
		<gsmserving mcc="228" mnc="01" lac="1919" id="16073" act_id="16073" rnc="-1" psc="-1" ss="-59" act="EDGE" rxlev="27"/>
	<gps time="20140921134233" lng="8.896585302465054" lat="47.520023020565546" alt="569.0" hdg="143.3878936767578" spe="32.42000198364258" accuracy="15.0" />
</scan>
</logfile>