<?xml version="1.0" encoding="UTF-8" ?>
<logfile manufacturer="Samsung" model="Nexus S" revision="4.4.4" swid="Radiobeacon" swver="0.7.9" exportver="0.7.9" >
<scan time="20140808174416" >
	<gps time="20140808174416" lng="7.195639876082336" lat="50.66424482787327" alt="102.0" hdg="340.36767578125" spe="6.206037521362305" accuracy="15.0" />
		<wifiap bssid="000ce36e2a07" md5essid="572363dfc3bef298f6c48e9ef931bc90" ssid="piz roseg" capa="[ESS]" ss="-92" ntiu="2462"/>
	<gps time="20140808174416" lng="7.195639876082336" lat="50.66424482787327" alt="102.0" hdg="340.36767578125" spe="6.206037521362305" accuracy="15.0" />
</scan>
<scan time="20140808174418" >
	<gps time="20140808174418" lng="7.195533373384125" lat="50.66437725592246" alt="104.0" hdg="333.5326843261719" spe="8.099319458007813" accuracy="15.0" />
		<wifiap bssid="002308f935ce" md5essid="b22bc31766acb56ef4cc5362622c0ae" ssid="wlan-f93578" capa="[WPA-PSK-CCMP+TKIP][WPA2-PSK-CCMP+TKIP][WPS][ESS]" ss="-91" ntiu="2437"/>
		<wifiap bssid="0022b0f28c9f" md5essid="cc8cbfe0c5ee2bd71568dc98d1dcf53" ssid="rumo" capa="[WPA-PSK-CCMP+TKIP][WPA2-PSK-CCMP+TKIP][WPS][ESS]" ss="-93" ntiu="2442"/>
		<wifiap bssid="000ce36e2a07" md5essid="572363dfc3bef298f6c48e9ef931bc90" ssid="piz roseg" capa="[ESS]" ss="-93" ntiu="2462"/>
		<wifiap bssid="001f3fd40dff" md5essid="1f53f71b02aa65985aa573649f9ce33" ssid="fritz!box fon wlan 7240" capa="[WPA-PSK-TKIP][WPA2-PSK-CCMP][WPS][ESS]" ss="-91" ntiu="2452"/>
		<wifiap bssid="00040ed7e60b" md5essid="d41d8cd98f0b24e980998ecf8427e" ssid="" capa="[WEP][ESS]" ss="-94" ntiu="2427"/>
	<gps time="20140808174418" lng="7.195533373384125" lat="50.66437725592246" alt="104.0" hdg="333.5326843261719" spe="8.099319458007813" accuracy="15.0" />
</scan>
<scan time="20140808174420" >
	<gps time="20140808174420" lng="7.195435240942359" lat="50.664497238176544" alt="102.0" hdg="338.03582763671875" spe="6.619353294372559" accuracy="15.0" />
		<wifiap bssid="002308f935ce" md5essid="b22bc31766acb56ef4cc5362622c0ae" ssid="wlan-f93578" capa="[WPA-PSK-CCMP+TKIP][WPA2-PSK-CCMP+TKIP][WPS][ESS]" ss="-93" ntiu="2437"/>
		<wifiap bssid="0022b0f28c9f" md5essid="cc8cbfe0c5ee2bd71568dc98d1dcf53" ssid="rumo" capa="[WPA-PSK-CCMP+TKIP][WPA2-PSK-CCMP+TKIP][WPS][ESS]" ss="-94" ntiu="2442"/>
		<wifiap bssid="000ce36e2a07" md5essid="572363dfc3bef298f6c48e9ef931bc90" ssid="piz roseg" capa="[ESS]" ss="-94" ntiu="2462"/>
		<wifiap bssid="001f3fd40dff" md5essid="1f53f71b02aa65985aa573649f9ce33" ssid="fritz!box fon wlan 7240" capa="[WPA-PSK-TKIP][WPA2-PSK-CCMP][WPS][ESS]" ss="-91" ntiu="2452"/>
		<wifiap bssid="00040ed7e60b" md5essid="d41d8cd98f0b24e980998ecf8427e" ssid="" capa="[WEP][ESS]" ss="-94" ntiu="2427"/>
		<wifiap bssid="9cc7a6833938" md5essid="69db51fc8ea14b33fd21cfe49c794d98" ssid="fritz!box 6360 cable" capa="[WPA-PSK-TKIP][WPA2-PSK-CCMP][WPS][ESS]" ss="-90" ntiu="2412"/>
	<gps time="20140808174420" lng="7.195435240942359" lat="50.664497238176544" alt="102.0" hdg="338.03582763671875" spe="6.619353294372559" accuracy="15.0" />
</scan>
<scan time="20140808174423" >
	<gps time="20140808174423" lng="7.195312830806122" lat="50.66465632061587" alt="99.0" hdg="341.2602233886719" spe="5.680334568023682" accuracy="10.0" />
		<wifiap bssid="002308f935ce" md5essid="b22bc31766acb56ef4cc5362622c0ae" ssid="wlan-f93578" capa="[WPA-PSK-CCMP+TKIP][WPA2-PSK-CCMP+TKIP][WPS][ESS]" ss="-93" ntiu="2437"/>
		<wifiap bssid="0022b0f28c9f" md5essid="cc8cbfe0c5ee2bd71568dc98d1dcf53" ssid="rumo" capa="[WPA-PSK-CCMP+TKIP][WPA2-PSK-CCMP+TKIP][WPS][ESS]" ss="-94" ntiu="2442"/>
		<wifiap bssid="000ce36e2a07" md5essid="572363dfc3bef298f6c48e9ef931bc90" ssid="piz roseg" capa="[ESS]" ss="-94" ntiu="2462"/>
		<wifiap bssid="001f3fd40dff" md5essid="1f53f71b02aa65985aa573649f9ce33" ssid="fritz!box fon wlan 7240" capa="[WPA-PSK-TKIP][WPA2-PSK-CCMP][WPS][ESS]" ss="-91" ntiu="2452"/>
		<wifiap bssid="00040ed7e60b" md5essid="d41d8cd98f0b24e980998ecf8427e" ssid="" capa="[WEP][ESS]" ss="-94" ntiu="2427"/>
		<wifiap bssid="9cc7a6833938" md5essid="69db51fc8ea14b33fd21cfe49c794d98" ssid="fritz!box 6360 cable" capa="[WPA-PSK-TKIP][WPA2-PSK-CCMP][WPS][ESS]" ss="-93" ntiu="2412"/>
		<wifiap bssid="00804847af70" md5essid="7e6832875eb3ffd2c75bf46f5644e2" ssid="4g_wlan" capa="[WPA-PSK-TKIP][WPA2-PSK-TKIP][ESS]" ss="-92" ntiu="2412"/>
	<gps time="20140808174423" lng="7.195312830806122" lat="50.66465632061587" alt="99.0" hdg="341.2602233886719" spe="5.680334568023682" accuracy="10.0" />
</scan>
<scan time="20140808174425" >
	<gps time="20140808174425" lng="7.195236368729711" lat="50.66476139828999" alt="99.0" hdg="343.49603271484375" spe="5.467370986938477" accuracy="15.0" />
		<wifiap bssid="002308f935ce" md5essid="b22bc31766acb56ef4cc5362622c0ae" ssid="wlan-f93578" capa="[WPA-PSK-CCMP+TKIP][WPA2-PSK-CCMP+TKIP][WPS][ESS]" ss="-92" ntiu="2437"/>
		<wifiap bssid="0022b0f28c9f" md5essid="cc8cbfe0c5ee2bd71568dc98d1dcf53" ssid="rumo" capa="[WPA-PSK-CCMP+TKIP][WPA2-PSK-CCMP+TKIP][WPS][ESS]" ss="-95" ntiu="2442"/>
		<wifiap bssid="000ce36e2a07" md5essid="572363dfc3bef298f6c48e9ef931bc90" ssid="piz roseg" capa="[ESS]" ss="-91" ntiu="2462"/>
		<wifiap bssid="9cc7a6833938" md5essid="69db51fc8ea14b33fd21cfe49c794d98" ssid="fritz!box 6360 cable" capa="[WPA-PSK-TKIP][WPA2-PSK-CCMP][WPS][ESS]" ss="-93" ntiu="2412"/>
		<wifiap bssid="00804847af70" md5essid="7e6832875eb3ffd2c75bf46f5644e2" ssid="4g_wlan" capa="[WPA-PSK-TKIP][WPA2-PSK-TKIP][ESS]" ss="-91" ntiu="2412"/>
	<gps time="20140808174425" lng="7.195236368729711" lat="50.66476139828999" alt="99.0" hdg="343.49603271484375" spe="5.467370986938477" accuracy="15.0" />
</scan>
<scan time="20140808174427" >
	<gps time="20140808174427" lng="7.195127239007022" lat="50.664876759360666" alt="101.0" hdg="334.7722473144531" spe="7.1564764976501465" accuracy="15.0" />
		<wifiap bssid="002308f935ce" md5essid="b22bc31766acb56ef4cc5362622c0ae" ssid="wlan-f93578" capa="[WPA-PSK-CCMP+TKIP][WPA2-PSK-CCMP+TKIP][WPS][ESS]" ss="-92" ntiu="2437"/>
		<wifiap bssid="0022b0f28c9f" md5essid="cc8cbfe0c5ee2bd71568dc98d1dcf53" ssid="rumo" capa="[WPA-PSK-CCMP+TKIP][WPA2-PSK-CCMP+TKIP][WPS][ESS]" ss="-95" ntiu="2442"/>
		<wifiap bssid="000ce36e2a07" md5essid="572363dfc3bef298f6c48e9ef931bc90" ssid="piz roseg" capa="[ESS]" ss="-91" ntiu="2462"/>
		<wifiap bssid="9cc7a6833938" md5essid="69db51fc8ea14b33fd21cfe49c794d98" ssid="fritz!box 6360 cable" capa="[WPA-PSK-TKIP][WPA2-PSK-CCMP][WPS][ESS]" ss="-93" ntiu="2412"/>
		<wifiap bssid="00804847af70" md5essid="7e6832875eb3ffd2c75bf46f5644e2" ssid="4g_wlan" capa="[WPA-PSK-TKIP][WPA2-PSK-TKIP][ESS]" ss="-90" ntiu="2412"/>
		<wifiap bssid="9c80df6507c8" md5essid="db1dadd4ca7b3232c4d277c0455f5e1" ssid="wlan-650741" capa="[WPA2-PSK-CCMP][WPS][ESS]" ss="-93" ntiu="2437"/>
	<gps time="20140808174427" lng="7.195127239007022" lat="50.664876759360666" alt="101.0" hdg="334.7722473144531" spe="7.1564764976501465" accuracy="15.0" />
</scan>
<scan time="20140808174429" >
	<gps time="20140808174429" lng="7.195009402223709" lat="50.66499639182503" alt="102.0" hdg="337.601318359375" spe="6.553779125213623" accuracy="10.0" />
		<wifiap bssid="002308f935ce" md5essid="b22bc31766acb56ef4cc5362622c0ae" ssid="wlan-f93578" capa="[WPA-PSK-CCMP+TKIP][WPA2-PSK-CCMP+TKIP][WPS][ESS]" ss="-92" ntiu="2437"/>
		<wifiap bssid="0022b0f28c9f" md5essid="cc8cbfe0c5ee2bd71568dc98d1dcf53" ssid="rumo" capa="[WPA-PSK-CCMP+TKIP][WPA2-PSK-CCMP+TKIP][WPS][ESS]" ss="-95" ntiu="2442"/>
		<wifiap bssid="000ce36e2a07" md5essid="572363dfc3bef298f6c48e9ef931bc90" ssid="piz roseg" capa="[ESS]" ss="-91" ntiu="2462"/>
		<wifiap bssid="9cc7a6833938" md5essid="69db51fc8ea14b33fd21cfe49c794d98" ssid="fritz!box 6360 cable" capa="[WPA-PSK-TKIP][WPA2-PSK-CCMP][WPS][ESS]" ss="-95" ntiu="2412"/>
		<wifiap bssid="00804847af70" md5essid="7e6832875eb3ffd2c75bf46f5644e2" ssid="4g_wlan" capa="[WPA-PSK-TKIP][WPA2-PSK-TKIP][ESS]" ss="-91" ntiu="2412"/>
		<wifiap bssid="9c80df6507c8" md5essid="db1dadd4ca7b3232c4d277c0455f5e1" ssid="wlan-650741" capa="[WPA2-PSK-CCMP][WPS][ESS]" ss="-91" ntiu="2437"/>
	<gps time="20140808174429" lng="7.195009402223709" lat="50.66499639182503" alt="102.0" hdg="337.601318359375" spe="6.553779125213623" accuracy="10.0" />
</scan>
<scan time="20140808174431" >
	<gps time="20140808174431" lng="7.194917152893095" lat="50.6651132552128" alt="104.0" hdg="338.1130065917969" spe="6.185222625732422" accuracy="10.0" />
		<wifiap bssid="000ce36e2a07" md5essid="572363dfc3bef298f6c48e9ef931bc90" ssid="piz roseg" capa="[ESS]" ss="-93" ntiu="2462"/>
		<wifiap bssid="9cc7a6833938" md5essid="69db51fc8ea14b33fd21cfe49c794d98" ssid="fritz!box 6360 cable" capa="[WPA-PSK-TKIP][WPA2-PSK-CCMP][WPS][ESS]" ss="-95" ntiu="2412"/>
		<wifiap bssid="00804847af70" md5essid="7e6832875eb3ffd2c75bf46f5644e2" ssid="4g_wlan" capa="[WPA-PSK-TKIP][WPA2-PSK-TKIP][ESS]" ss="-91" ntiu="2412"/>
		<wifiap bssid="9c80df6507c8" md5essid="db1dadd4ca7b3232c4d277c0455f5e1" ssid="wlan-650741" capa="[WPA2-PSK-CCMP][WPS][ESS]" ss="-91" ntiu="2437"/>
	<gps time="20140808174431" lng="7.194917152893095" lat="50.6651132552128" alt="104.0" hdg="338.1130065917969" spe="6.185222625732422" accuracy="10.0" />
</scan>
<scan time="20140808174433" >
	<gps time="20140808174433" lng="7.194810246670557" lat="50.66523417472727" alt="102.0" hdg="341.33575439453125" spe="6.258312702178955" accuracy="10.0" />
		<wifiap bssid="000ce36e2a07" md5essid="572363dfc3bef298f6c48e9ef931bc90" ssid="piz roseg" capa="[ESS]" ss="-90" ntiu="2462"/>
		<wifiap bssid="9cc7a6833938" md5essid="69db51fc8ea14b33fd21cfe49c794d98" ssid="fritz!box 6360 cable" capa="[WPA-PSK-TKIP][WPA2-PSK-CCMP][WPS][ESS]" ss="-95" ntiu="2412"/>
		<wifiap bssid="00804847af70" md5essid="7e6832875eb3ffd2c75bf46f5644e2" ssid="4g_wlan" capa="[WPA-PSK-TKIP][WPA2-PSK-TKIP][ESS]" ss="-91" ntiu="2412"/>
		<wifiap bssid="9c80df6507c8" md5essid="db1dadd4ca7b3232c4d277c0455f5e1" ssid="wlan-650741" capa="[WPA2-PSK-CCMP][WPS][ESS]" ss="-93" ntiu="2437"/>
	<gps time="20140808174433" lng="7.194810246670557" lat="50.66523417472727" alt="102.0" hdg="341.33575439453125" spe="6.258312702178955" accuracy="10.0" />
</scan>
<scan time="20140808174435" >
	<gps time="20140808174435" lng="7.1947034630932025" lat="50.665363317038164" alt="99.0" hdg="334.01312255859375" spe="7.939826488494873" accuracy="15.0" />
		<wifiap bssid="000ce36e2a07" md5essid="572363dfc3bef298f6c48e9ef931bc90" ssid="piz roseg" capa="[ESS]" ss="-90" ntiu="2462"/>
		<wifiap bssid="9c80df6507c8" md5essid="db1dadd4ca7b3232c4d277c0455f5e1" ssid="wlan-650741" capa="[WPA2-PSK-CCMP][WPS][ESS]" ss="-93" ntiu="2437"/>
		<wifiap bssid="0022b0f28c9f" md5essid="cc8cbfe0c5ee2bd71568dc98d1dcf53" ssid="rumo" capa="[WPA-PSK-CCMP+TKIP][WPA2-PSK-CCMP+TKIP][WPS][ESS]" ss="-90" ntiu="2442"/>
		<wifiap bssid="040b6b236211" md5essid="bdf92fb6fd763c38efa81c78c6bdf579" ssid="telekom" capa="[ESS]" ss="-93" ntiu="2447"/>
	<gps time="20140808174435" lng="7.1947034630932025" lat="50.665363317038164" alt="99.0" hdg="334.01312255859375" spe="7.939826488494873" accuracy="15.0" />
</scan>
<scan time="20140808174437" >
	<gps time="20140808174437" lng="7.194601449976686" lat="50.66549057984014" alt="99.0" hdg="336.48876953125" spe="6.5439276695251465" accuracy="15.0" />
		<wifiap bssid="000ce36e2a07" md5essid="572363dfc3bef298f6c48e9ef931bc90" ssid="piz roseg" capa="[ESS]" ss="-90" ntiu="2462"/>
		<wifiap bssid="9c80df6507c8" md5essid="db1dadd4ca7b3232c4d277c0455f5e1" ssid="wlan-650741" capa="[WPA2-PSK-CCMP][WPS][ESS]" ss="-93" ntiu="2437"/>
		<wifiap bssid="0022b0f28c9f" md5essid="cc8cbfe0c5ee2bd71568dc98d1dcf53" ssid="rumo" capa="[WPA-PSK-CCMP+TKIP][WPA2-PSK-CCMP+TKIP][WPS][ESS]" ss="-88" ntiu="2442"/>
		<wifiap bssid="040b6b236211" md5essid="bdf92fb6fd763c38efa81c78c6bdf579" ssid="telekom" capa="[ESS]" ss="-93" ntiu="2447"/>
		<wifiap bssid="24651105d03e" md5essid="acfedd974bcb282a3aeed5b1cebe6b3" ssid="fritz!box 6320 v2 cable" capa="[WPA-PSK-TKIP][WPA2-PSK-CCMP][WPS][ESS]" ss="-95" ntiu="2472"/>
	<gps time="20140808174437" lng="7.194601449976686" lat="50.66549057984014" alt="99.0" hdg="336.48876953125" spe="6.5439276695251465" accuracy="15.0" />
</scan>
<scan time="20140808174439" >
	<gps time="20140808174439" lng="7.194497889640084" lat="50.6656260648017" alt="97.0" hdg="336.48876953125" spe="7.230696678161621" accuracy="15.0" />
		<wifiap bssid="0022b0f28c9f" md5essid="cc8cbfe0c5ee2bd71568dc98d1dcf53" ssid="rumo" capa="[WPA-PSK-CCMP+TKIP][WPA2-PSK-CCMP+TKIP][WPS][ESS]" ss="-91" ntiu="2442"/>
		<wifiap bssid="040b6b236211" md5essid="bdf92fb6fd763c38efa81c78c6bdf579" ssid="telekom" capa="[ESS]" ss="-93" ntiu="2447"/>
		<wifiap bssid="24651105d03e" md5essid="acfedd974bcb282a3aeed5b1cebe6b3" ssid="fritz!box 6320 v2 cable" capa="[WPA-PSK-TKIP][WPA2-PSK-CCMP][WPS][ESS]" ss="-94" ntiu="2472"/>
		<wifiap bssid="586d8f37cc80" md5essid="9dd38ddaeb2db7b3c632bfd3c685ec83" ssid="eumelomat" capa="[WPA2-PSK-CCMP][WPS][ESS]" ss="-95" ntiu="2462"/>
		<wifiap bssid="c42795bc71f8" md5essid="7622eb962211365ed8569adeba97b58" ssid="upc2250836" capa="[WPA-PSK-CCMP+TKIP][WPA2-PSK-CCMP+TKIP][ESS]" ss="-96" ntiu="2412"/>
	<gps time="20140808174439" lng="7.194497889640084" lat="50.6656260648017" alt="97.0" hdg="336.48876953125" spe="7.230696678161621" accuracy="15.0" />
</scan>
<scan time="20140808174441" >
	<gps time="20140808174441" lng="7.194399352606049" lat="50.66575026412012" alt="98.0" hdg="336.48876953125" spe="7.343705177307129" accuracy="15.0" />
		<wifiap bssid="0022b0f28c9f" md5essid="cc8cbfe0c5ee2bd71568dc98d1dcf53" ssid="rumo" capa="[WPA-PSK-CCMP+TKIP][WPA2-PSK-CCMP+TKIP][WPS][ESS]" ss="-88" ntiu="2442"/>
		<wifiap bssid="24651105d03e" md5essid="acfedd974bcb282a3aeed5b1cebe6b3" ssid="fritz!box 6320 v2 cable" capa="[WPA-PSK-TKIP][WPA2-PSK-CCMP][WPS][ESS]" ss="-94" ntiu="2472"/>
		<wifiap bssid="586d8f37cc80" md5essid="9dd38ddaeb2db7b3c632bfd3c685ec83" ssid="eumelomat" capa="[WPA2-PSK-CCMP][WPS][ESS]" ss="-95" ntiu="2462"/>
		<wifiap bssid="c42795bc71f8" md5essid="7622eb962211365ed8569adeba97b58" ssid="upc2250836" capa="[WPA-PSK-CCMP+TKIP][WPA2-PSK-CCMP+TKIP][ESS]" ss="-96" ntiu="2412"/>
		<wifiap bssid="9c80df6507c8" md5essid="db1dadd4ca7b3232c4d277c0455f5e1" ssid="wlan-650741" capa="[WPA2-PSK-CCMP][WPS][ESS]" ss="-92" ntiu="2437"/>
		<wifiap bssid="001a4f9a8454" md5essid="46b1af5d6aa3d60bc5966776223e0" ssid="tomtom7" capa="[WPA-PSK-TKIP][ESS]" ss="-93" ntiu="2467"/>
	<gps time="20140808174441" lng="7.194399352606049" lat="50.66575026412012" alt="98.0" hdg="336.48876953125" spe="7.343705177307129" accuracy="15.0" />
</scan>
<scan time="20140808174443" >
	<gps time="20140808174443" lng="7.194301323416853" lat="50.66587786593081" alt="96.0" hdg="335.2294616699219" spe="8.199911117553711" accuracy="15.0" />
		<wifiap bssid="0022b0f28c9f" md5essid="cc8cbfe0c5ee2bd71568dc98d1dcf53" ssid="rumo" capa="[WPA-PSK-CCMP+TKIP][WPA2-PSK-CCMP+TKIP][WPS][ESS]" ss="-88" ntiu="2442"/>
		<wifiap bssid="24651105d03e" md5essid="acfedd974bcb282a3aeed5b1cebe6b3" ssid="fritz!box 6320 v2 cable" capa="[WPA-PSK-TKIP][WPA2-PSK-CCMP][WPS][ESS]" ss="-94" ntiu="2472"/>
		<wifiap bssid="586d8f37cc80" md5essid="9dd38ddaeb2db7b3c632bfd3c685ec83" ssid="eumelomat" capa="[WPA2-PSK-CCMP][WPS][ESS]" ss="-95" ntiu="2462"/>
		<wifiap bssid="c42795bc71f8" md5essid="7622eb962211365ed8569adeba97b58" ssid="upc2250836" capa="[WPA-PSK-CCMP+TKIP][WPA2-PSK-CCMP+TKIP][ESS]" ss="-96" ntiu="2412"/>
		<wifiap bssid="9c80df6507c8" md5essid="db1dadd4ca7b3232c4d277c0455f5e1" ssid="wlan-650741" capa="[WPA2-PSK-CCMP][WPS][ESS]" ss="-92" ntiu="2437"/>
		<wifiap bssid="001a4f9a8454" md5essid="46b1af5d6aa3d60bc5966776223e0" ssid="tomtom7" capa="[WPA-PSK-TKIP][ESS]" ss="-93" ntiu="2467"/>
		<wifiap bssid="040b6b236211" md5essid="bdf92fb6fd763c38efa81c78c6bdf579" ssid="telekom" capa="[ESS]" ss="-95" ntiu="2447"/>
	<gps time="20140808174443" lng="7.194301323416853" lat="50.66587786593081" alt="96.0" hdg="335.2294616699219" spe="8.199911117553711" accuracy="15.0" />
</scan>
<scan time="20140808174445" >
	<gps time="20140808174445" lng="7.19419941353419" lat="50.66600826501574" alt="99.0" hdg="335.2294616699219" spe="8.102317810058594" accuracy="15.0" />
		<wifiap bssid="0022b0f28c9f" md5essid="cc8cbfe0c5ee2bd71568dc98d1dcf53" ssid="rumo" capa="[WPA-PSK-CCMP+TKIP][WPA2-PSK-CCMP+TKIP][WPS][ESS]" ss="-89" ntiu="2442"/>
		<wifiap bssid="c42795bc71f8" md5essid="7622eb962211365ed8569adeba97b58" ssid="upc2250836" capa="[WPA-PSK-CCMP+TKIP][WPA2-PSK-CCMP+TKIP][ESS]" ss="-96" ntiu="2412"/>
		<wifiap bssid="9c80df6507c8" md5essid="db1dadd4ca7b3232c4d277c0455f5e1" ssid="wlan-650741" capa="[WPA2-PSK-CCMP][WPS][ESS]" ss="-92" ntiu="2437"/>
		<wifiap bssid="001a4f9a8454" md5essid="46b1af5d6aa3d60bc5966776223e0" ssid="tomtom7" capa="[WPA-PSK-TKIP][ESS]" ss="-93" ntiu="2467"/>
		<wifiap bssid="040b6b236211" md5essid="bdf92fb6fd763c38efa81c78c6bdf579" ssid="telekom" capa="[ESS]" ss="-95" ntiu="2447"/>
	<gps time="20140808174445" lng="7.19419941353419" lat="50.66600826501574" alt="99.0" hdg="335.2294616699219" spe="8.102317810058594" accuracy="15.0" />
</scan>
<scan time="20140808174447" >
	<gps time="20140808174447" lng="7.194144345795154" lat="50.6661123475347" alt="101.0" hdg="343.828857421875" spe="5.994289398193359" accuracy="15.0" />
		<wifiap bssid="0022b0f28c9f" md5essid="cc8cbfe0c5ee2bd71568dc98d1dcf53" ssid="rumo" capa="[WPA-PSK-CCMP+TKIP][WPA2-PSK-CCMP+TKIP][WPS][ESS]" ss="-89" ntiu="2442"/>
		<wifiap bssid="c42795bc71f8" md5essid="7622eb962211365ed8569adeba97b58" ssid="upc2250836" capa="[WPA-PSK-CCMP+TKIP][WPA2-PSK-CCMP+TKIP][ESS]" ss="-96" ntiu="2412"/>
		<wifiap bssid="040b6b236211" md5essid="bdf92fb6fd763c38efa81c78c6bdf579" ssid="telekom" capa="[ESS]" ss="-90" ntiu="2447"/>
		<wifiap bssid="001f3fd40dff" md5essid="1f53f71b02aa65985aa573649f9ce33" ssid="fritz!box fon wlan 7240" capa="[WPA-PSK-TKIP][WPA2-PSK-CCMP][WPS][ESS]" ss="-92" ntiu="2452"/>
		<wifiap bssid="f4c71438f4ec" md5essid="1bd1d61da4875642276d5c7d40c6b23a" ssid="wlan-f4ec28" capa="[WPA2-PSK-CCMP][WPS][ESS]" ss="-94" ntiu="2452"/>
		<wifiap bssid="002308f935ce" md5essid="b22bc31766acb56ef4cc5362622c0ae" ssid="wlan-f93578" capa="[WPA-PSK-CCMP+TKIP][WPA2-PSK-CCMP+TKIP][WPS][ESS]" ss="-96" ntiu="2437"/>
	<gps time="20140808174447" lng="7.194144345795154" lat="50.6661123475347" alt="101.0" hdg="343.828857421875" spe="5.994289398193359" accuracy="15.0" />
</scan>
<scan time="20140808174449" >
	<gps time="20140808174449" lng="7.194034036153382" lat="50.666235321584566" alt="101.0" hdg="335.8973388671875" spe="7.987429141998291" accuracy="15.0" />
		<wifiap bssid="0022b0f28c9f" md5essid="cc8cbfe0c5ee2bd71568dc98d1dcf53" ssid="rumo" capa="[WPA-PSK-CCMP+TKIP][WPA2-PSK-CCMP+TKIP][WPS][ESS]" ss="-86" ntiu="2442"/>
		<wifiap bssid="040b6b236211" md5essid="bdf92fb6fd763c38efa81c78c6bdf579" ssid="telekom" capa="[ESS]" ss="-90" ntiu="2447"/>
		<wifiap bssid="001f3fd40dff" md5essid="1f53f71b02aa65985aa573649f9ce33" ssid="fritz!box fon wlan 7240" capa="[WPA-PSK-TKIP][WPA2-PSK-CCMP][WPS][ESS]" ss="-90" ntiu="2452"/>
		<wifiap bssid="f4c71438f4ec" md5essid="1bd1d61da4875642276d5c7d40c6b23a" ssid="wlan-f4ec28" capa="[WPA2-PSK-CCMP][WPS][ESS]" ss="-94" ntiu="2452"/>
		<wifiap bssid="002308f935ce" md5essid="b22bc31766acb56ef4cc5362622c0ae" ssid="wlan-f93578" capa="[WPA-PSK-CCMP+TKIP][WPA2-PSK-CCMP+TKIP][WPS][ESS]" ss="-96" ntiu="2437"/>
		<wifiap bssid="001a4f9a8454" md5essid="46b1af5d6aa3d60bc5966776223e0" ssid="tomtom7" capa="[WPA-PSK-TKIP][ESS]" ss="-94" ntiu="2467"/>
		<wifiap bssid="002401197207" md5essid="cf6f83af9786671aff636f989852dfe6" ssid="dlink" capa="[WPS][WEP][ESS]" ss="-93" ntiu="2437"/>
		<wifiap bssid="000ce36e2a07" md5essid="572363dfc3bef298f6c48e9ef931bc90" ssid="piz roseg" capa="[ESS]" ss="-93" ntiu="2462"/>
	<gps time="20140808174449" lng="7.194034036153382" lat="50.666235321584566" alt="101.0" hdg="335.8973388671875" spe="7.987429141998291" accuracy="15.0" />
</scan>
<scan time="20140808174451" >
	<gps time="20140808174451" lng="7.193928560703313" lat="50.666359519764384" alt="101.0" hdg="333.4395446777344" spe="8.78278923034668" accuracy="15.0" />
		<wifiap bssid="0022b0f28c9f" md5essid="cc8cbfe0c5ee2bd71568dc98d1dcf53" ssid="rumo" capa="[WPA-PSK-CCMP+TKIP][WPA2-PSK-CCMP+TKIP][WPS][ESS]" ss="-86" ntiu="2442"/>
		<wifiap bssid="040b6b236211" md5essid="bdf92fb6fd763c38efa81c78c6bdf579" ssid="telekom" capa="[ESS]" ss="-90" ntiu="2447"/>
		<wifiap bssid="001f3fd40dff" md5essid="1f53f71b02aa65985aa573649f9ce33" ssid="fritz!box fon wlan 7240" capa="[WPA-PSK-TKIP][WPA2-PSK-CCMP][WPS][ESS]" ss="-90" ntiu="2452"/>
		<wifiap bssid="f4c71438f4ec" md5essid="1bd1d61da4875642276d5c7d40c6b23a" ssid="wlan-f4ec28" capa="[WPA2-PSK-CCMP][WPS][ESS]" ss="-94" ntiu="2452"/>
		<wifiap bssid="002308f935ce" md5essid="b22bc31766acb56ef4cc5362622c0ae" ssid="wlan-f93578" capa="[WPA-PSK-CCMP+TKIP][WPA2-PSK-CCMP+TKIP][WPS][ESS]" ss="-89" ntiu="2437"/>
		<wifiap bssid="001a4f9a8454" md5essid="46b1af5d6aa3d60bc5966776223e0" ssid="tomtom7" capa="[WPA-PSK-TKIP][ESS]" ss="-94" ntiu="2467"/>
		<wifiap bssid="002401197207" md5essid="cf6f83af9786671aff636f989852dfe6" ssid="dlink" capa="[WPS][WEP][ESS]" ss="-93" ntiu="2437"/>
		<wifiap bssid="000ce36e2a07" md5essid="572363dfc3bef298f6c48e9ef931bc90" ssid="piz roseg" capa="[ESS]" ss="-90" ntiu="2462"/>
		<wifiap bssid="1449e0d71ea8" md5essid="2729a5402c7c443381785de35f91510" ssid="upc248298192" capa="[WPA2-PSK-CCMP+TKIP][WPS][ESS]" ss="-90" ntiu="2412"/>
	<gps time="20140808174451" lng="7.193928560703313" lat="50.666359519764384" alt="101.0" hdg="333.4395446777344" spe="8.78278923034668" accuracy="15.0" />
</scan>
<scan time="20140808174453" >
	<gps time="20140808174453" lng="7.193838627933054" lat="50.66648454538017" alt="99.0" hdg="331.7134704589844" spe="8.454724311828613" accuracy="15.0" />
		<wifiap bssid="0022b0f28c9f" md5essid="cc8cbfe0c5ee2bd71568dc98d1dcf53" ssid="rumo" capa="[WPA-PSK-CCMP+TKIP][WPA2-PSK-CCMP+TKIP][WPS][ESS]" ss="-89" ntiu="2442"/>
	<gps time="20140808174453" lng="7.193838627933054" lat="50.66648454538017" alt="99.0" hdg="331.7134704589844" spe="8.454724311828613" accuracy="15.0" />
</scan>
</logfile>