<?xml version="1.0" encoding="UTF-8" ?>
<logfile manufacturer="Samsung" model="Nexus S" revision="4.3.1" swid="Radiobeacon" swver="0.7.9" exportver="0.7.9" >
<scan time="20140404213357" >
	<gps time="20140404213357" lng="6.951874543753531" lat="51.370519502594476" alt="167.0" hdg="242.45956420898438" spe="3.0203731060028076" accuracy="15.0" />
		<wifiap bssid="14d64de2f79e" md5essid="794527d22c85c64677d6fa965bd1215" ssid="breakout" capa="[WPA-PSK-CCMP+TKIP][WPA2-PSK-CCMP+TKIP][WPS][ESS]" ss="-96" ntiu="2437"/>
		<wifiap bssid="9cc7a65c6893" md5essid="312014efa1a79d4f8881eabf9b157878" ssid="wlan_ba" capa="[WPA2-PSK-CCMP][WPS][ESS]" ss="-97" ntiu="2412"/>
	<gps time="20140404213357" lng="6.951874543753531" lat="51.370519502594476" alt="167.0" hdg="242.45956420898438" spe="3.0203731060028076" accuracy="15.0" />
</scan>
<scan time="20140404213359" >
	<gps time="20140404213359" lng="6.951757219960221" lat="51.37050476366533" alt="170.0" hdg="263.24896240234375" spe="3.199000358581543" accuracy="10.0" />
		<wifiap bssid="907240155e20" md5essid="84bdb7ef64595e243b9265f34a1fbed" ssid="wolfsnetcave" capa="[WPA2-PSK-CCMP][ESS]" ss="-93" ntiu="2462"/>
		<wifiap bssid="9cc7a65c6893" md5essid="312014efa1a79d4f8881eabf9b157878" ssid="wlan_ba" capa="[WPA2-PSK-CCMP][WPS][ESS]" ss="-97" ntiu="2412"/>
	<gps time="20140404213359" lng="6.951757219960221" lat="51.37050476366533" alt="170.0" hdg="263.24896240234375" spe="3.199000358581543" accuracy="10.0" />
</scan>
<scan time="20140404213401" >
	<gps time="20140404213401" lng="6.951679515363521" lat="51.370492044990904" alt="172.0" hdg="265.39697265625" spe="2.238901376724243" accuracy="10.0" />
		<wifiap bssid="907240155e20" md5essid="84bdb7ef64595e243b9265f34a1fbed" ssid="wolfsnetcave" capa="[WPA2-PSK-CCMP][ESS]" ss="-93" ntiu="2462"/>
		<wifiap bssid="9cc7a65c6893" md5essid="312014efa1a79d4f8881eabf9b157878" ssid="wlan_ba" capa="[WPA2-PSK-CCMP][WPS][ESS]" ss="-93" ntiu="2412"/>
		<wifiap bssid="001349ee88c8" md5essid="269be579adf7984e18eadbedda3b3f3" ssid="homewlan" capa="[WPA-PSK-TKIP][WPA2-PSK-CCMP-preauth][ESS]" ss="-92" ntiu="2437"/>
		<wifiap bssid="84a8e4e75e44" md5essid="92e21f8eeccde7dd46a4bfb3538e7f" ssid="wlan-5e4450" capa="[WPA2-PSK-CCMP][WPS][ESS]" ss="-94" ntiu="2437"/>
	<gps time="20140404213401" lng="6.951679515363521" lat="51.370492044990904" alt="172.0" hdg="265.39697265625" spe="2.238901376724243" accuracy="10.0" />
</scan>
<scan time="20140404213403" >
	<gps time="20140404213403" lng="6.951606275213141" lat="51.37047898651218" alt="173.0" hdg="262.72650146484375" spe="2.5314111709594727" accuracy="10.0" />
		<wifiap bssid="9cc7a65c6893" md5essid="312014efa1a79d4f8881eabf9b157878" ssid="wlan_ba" capa="[WPA2-PSK-CCMP][WPS][ESS]" ss="-95" ntiu="2412"/>
		<wifiap bssid="001349ee88c8" md5essid="269be579adf7984e18eadbedda3b3f3" ssid="homewlan" capa="[WPA-PSK-TKIP][WPA2-PSK-CCMP-preauth][ESS]" ss="-92" ntiu="2437"/>
		<wifiap bssid="84a8e4e75e44" md5essid="92e21f8eeccde7dd46a4bfb3538e7f" ssid="wlan-5e4450" capa="[WPA2-PSK-CCMP][WPS][ESS]" ss="-94" ntiu="2437"/>
		<wifiap bssid="12a096dee0ac" md5essid="7b2b3ebfb2fd35c6dceba8daf5664b4" ssid="direct-lq-bravia" capa="[WPA2-PSK-CCMP][WPS][ESS][P2P]" ss="-91" ntiu="2412"/>
	<gps time="20140404213403" lng="6.951606275213141" lat="51.37047898651218" alt="173.0" hdg="262.72650146484375" spe="2.5314111709594727" accuracy="10.0" />
</scan>
<scan time="20140404213412" >
	<gps time="20140404213412" lng="6.951368195778427" lat="51.3704947594149" alt="167.0" hdg="285.7295227050781" spe="2.7454426288604736" accuracy="10.0" />
		<wifiap bssid="9cc7a65c6893" md5essid="312014efa1a79d4f8881eabf9b157878" ssid="wlan_ba" capa="[WPA2-PSK-CCMP][WPS][ESS]" ss="-90" ntiu="2412"/>
		<wifiap bssid="001349ee88c8" md5essid="269be579adf7984e18eadbedda3b3f3" ssid="homewlan" capa="[WPA-PSK-TKIP][WPA2-PSK-CCMP-preauth][ESS]" ss="-81" ntiu="2437"/>
		<wifiap bssid="84a8e4e75e44" md5essid="92e21f8eeccde7dd46a4bfb3538e7f" ssid="wlan-5e4450" capa="[WPA2-PSK-CCMP][WPS][ESS]" ss="-94" ntiu="2437"/>
		<wifiap bssid="12a096dee0ac" md5essid="7b2b3ebfb2fd35c6dceba8daf5664b4" ssid="direct-lq-bravia" capa="[WPA2-PSK-CCMP][WPS][ESS][P2P]" ss="-91" ntiu="2412"/>
	<gps time="20140404213412" lng="6.951368195778427" lat="51.3704947594149" alt="167.0" hdg="285.7295227050781" spe="2.7454426288604736" accuracy="10.0" />
</scan>
<scan time="20140404213414" >
	<gps time="20140404213414" lng="6.951295011612975" lat="51.37050443047573" alt="163.0" hdg="281.2020568847656" spe="2.5038979053497314" accuracy="10.0" />
		<wifiap bssid="9cc7a65c6893" md5essid="312014efa1a79d4f8881eabf9b157878" ssid="wlan_ba" capa="[WPA2-PSK-CCMP][WPS][ESS]" ss="-90" ntiu="2412"/>
		<wifiap bssid="001349ee88c8" md5essid="269be579adf7984e18eadbedda3b3f3" ssid="homewlan" capa="[WPA-PSK-TKIP][WPA2-PSK-CCMP-preauth][ESS]" ss="-89" ntiu="2437"/>
		<wifiap bssid="12a096dee0ac" md5essid="7b2b3ebfb2fd35c6dceba8daf5664b4" ssid="direct-lq-bravia" capa="[WPA2-PSK-CCMP][WPS][ESS][P2P]" ss="-85" ntiu="2412"/>
	<gps time="20140404213414" lng="6.951295011612975" lat="51.37050443047573" alt="163.0" hdg="281.2020568847656" spe="2.5038979053497314" accuracy="10.0" />
</scan>
</logfile>